lonboard/__init__.py
lonboard/__main__.py
lonboard/_base.py
lonboard/_cli.py
lonboard/_compat.py
lonboard/_constants.py
lonboard/_environment.py
lonboard/_html_export.py
lonboard/_map.py
lonboard/_serialization.py
lonboard/_utils.py
lonboard/_version.py
lonboard/_viewport.py
lonboard/_viz.py
lonboard/basemap.py
lonboard/colormap.py
lonboard/controls.py
lonboard/layer_extension.py
lonboard/py.typed
lonboard/view_state.py
lonboard/_geoarrow/__init__.py
lonboard/_geoarrow/_duckdb.py
lonboard/_geoarrow/box_to_polygon.py
lonboard/_geoarrow/c_stream_import.py
lonboard/_geoarrow/crs.py
lonboard/_geoarrow/extension_types.py
lonboard/_geoarrow/geopandas_interop.py
lonboard/_geoarrow/movingpandas_interop.py
lonboard/_geoarrow/parse_wkb.py
lonboard/_geoarrow/row_index.py
lonboard/_geoarrow/utils.py
lonboard/_geoarrow/ops/__init__.py
lonboard/_geoarrow/ops/bbox.py
lonboard/_geoarrow/ops/centroid.py
lonboard/_geoarrow/ops/coord_layout.py
lonboard/_geoarrow/ops/reproject.py
lonboard/_h3/__init__.py
lonboard/_h3/_h3_to_str.py
lonboard/_h3/_str_to_h3.py
lonboard/_h3/_validate_h3_cell.py
lonboard/_validators/__init__.py
lonboard/_validators/types.py
lonboard/_vendor/__init__.py
lonboard/_vendor/matplotlib/__init__.py
lonboard/_vendor/matplotlib/_color_data.py
lonboard/_vendor/matplotlib/colors.py
lonboard/experimental/__init__.py
lonboard/experimental/_layer.py
lonboard/experimental/_surface.py
lonboard/experimental/traits.py
lonboard/experimental/view.py
lonboard/layer/__init__.py
lonboard/layer/_a5.py
lonboard/layer/_arc.py
lonboard/layer/_base.py
lonboard/layer/_bitmap.py
lonboard/layer/_column.py
lonboard/layer/_geohash.py
lonboard/layer/_h3.py
lonboard/layer/_heatmap.py
lonboard/layer/_path.py
lonboard/layer/_point_cloud.py
lonboard/layer/_polygon.py
lonboard/layer/_s2.py
lonboard/layer/_scatterplot.py
lonboard/layer/_trips.py
lonboard/static/index.css
lonboard/static/index.js
lonboard/traits/__init__.py
lonboard/traits/_a5.py
lonboard/traits/_base.py
lonboard/traits/_color.py
lonboard-0.13.0.dist-info/METADATA
lonboard-0.13.0.dist-info/WHEEL
lonboard-0.13.0.dist-info/entry_points.txt
lonboard-0.13.0.dist-info/licenses/LICENSE
lonboard-0.13.0.dist-info/RECORD
