Metadata-Version: 2.4
Name: lonboard
Version: 0.13.0
Summary: Fast, interactive geospatial data visualization in Jupyter.
Project-URL: homepage, https://developmentseed.org/lonboard/latest/
Project-URL: documentation, https://developmentseed.org/lonboard/latest/
Project-URL: repository, https://github.com/developmentseed/lonboard
Project-URL: issues, https://github.com/developmentseed/lonboard/issues
Project-URL: changelog, https://github.com/developmentseed/lonboard/blob/main/CHANGELOG.md
Author-email: Kyle Barron <kyle@developmentseed.org>
License-Expression: MIT
License-File: LICENSE
Keywords: GIS,cartography,geopandas,pandas,shapely,visualization
Classifier: Development Status :: 4 - Beta
Classifier: Framework :: Jupyter
Classifier: Framework :: Jupyter :: JupyterLab
Classifier: Intended Audience :: Science/Research
Classifier: License :: OSI Approved :: MIT License
Classifier: Operating System :: OS Independent
Classifier: Programming Language :: Python :: 3
Classifier: Programming Language :: Python :: 3 :: Only
Classifier: Topic :: Scientific/Engineering :: GIS
Requires-Python: >=3.10
Requires-Dist: anywidget~=0.9.0
Requires-Dist: arro3-compute>=0.4.1
Requires-Dist: arro3-core>=0.4.1
Requires-Dist: arro3-io>=0.4.1
Requires-Dist: geoarrow-rust-core>=0.5.2
Requires-Dist: ipywidgets>=7.6.0
Requires-Dist: numpy>=1.14
Requires-Dist: pyproj>=3.3
Requires-Dist: traitlets>=5.7.1
Requires-Dist: typing-extensions>=4.12.0
Provides-Extra: cli
Requires-Dist: click>=8.1.7; extra == 'cli'
Requires-Dist: pyogrio>=0.8; extra == 'cli'
Requires-Dist: shapely>=2; extra == 'cli'
Provides-Extra: geopandas
Requires-Dist: geopandas>=0.13; extra == 'geopandas'
Requires-Dist: pandas>=2; extra == 'geopandas'
Requires-Dist: pyarrow>=16; extra == 'geopandas'
Requires-Dist: shapely>=2; extra == 'geopandas'
Provides-Extra: movingpandas
Requires-Dist: movingpandas>=0.17; extra == 'movingpandas'
